root_domain/__init__.py
root_domain/main.py
root_domain-0.0.1.dist-info/LICENSE
root_domain-0.0.1.dist-info/METADATA
root_domain-0.0.1.dist-info/WHEEL
root_domain-0.0.1.dist-info/entry_points.txt
root_domain-0.0.1.dist-info/top_level.txt
root_domain-0.0.1.dist-info/RECORD
