Metadata-Version: 2.1
Name: root-domain
Version: 0.0.1
Summary: Extract root from domain
Home-page: https://gitlab.com/Zer1t0/root-domain
Author: Eloy Perez
Author-email: zer1t0ps@protonmail.com
License: UNKNOWN
Platform: UNKNOWN
Classifier: Programming Language :: Python :: 3
Classifier: License :: OSI Approved :: GNU General Public License v3 (GPLv3)
Requires-Dist: tldextract
Requires-Dist: validators
